sego/__init__.py
sego/sego.py
sego/Exceptions/ClientErrorResponses.py
sego/Exceptions/ClientExceptions.py
sego/Exceptions/ConfigurationException.py
sego/Exceptions/HTTPVerbException.py
sego/Exceptions/InformationResponses.py
sego/Exceptions/MiddlewareException.py
sego/Exceptions/RedirectionMessages.py
sego/Exceptions/RoutingExceptions.py
sego/Exceptions/SegoBaseException.py
sego/Exceptions/ServerErrorResponses.py
sego/Exceptions/SuccessfulResponses.py
sego/Exceptions/__init__.py
sego/Middleware/Middleware.py
sego/Middleware/MiddlewareManager.py
sego/Middleware/__init__.py
sego/Routing/Route.py
sego/Routing/Router.py
sego/Routing/Verb.py
sego/Routing/__init__.py
sego/Views/Views.py
sego/Views/__init__.py
sego-0.1.4.0.dist-info/METADATA
sego-0.1.4.0.dist-info/WHEEL
sego-0.1.4.0.dist-info/top_level.txt
sego-0.1.4.0.dist-info/RECORD
