Metadata-Version: 2.1
Name: sego
Version: 0.1.4.0
Summary: A web and micro-service framework for data analysts
Home-page: https://github.com/sambe-consulting/sego
Author: Sambe Consulting
Author-email: development@sambe.co.za
License: Apache License 2.0
Platform: UNKNOWN
Classifier: License :: OSI Approved :: Apache Software License
Classifier: Programming Language :: Python :: 3
Classifier: Programming Language :: Python :: 3.7
Requires-Dist: flask
Requires-Dist: confo
Requires-Dist: orator
Requires-Dist: makefun
